{
  "me": {
    "foundation": {
      "sage": {
        "10": {
          "value": "#f7f7f2",
          "type": "color"
        },
        "20": {
          "value": "#efefe5",
          "type": "color"
        },
        "30": {
          "value": "#e3e3d1",
          "type": "color"
        },
        "40": {
          "value": "#d6d6be",
          "type": "color"
        },
        "50": {
          "value": "#cacaaa",
          "type": "color"
        },
        "60": {
          "value": "#b6b699",
          "type": "color"
        },
        "70": {
          "value": "#a2a288",
          "type": "color"
        },
        "80": {
          "value": "#989880",
          "type": "color"
        },
        "90": {
          "value": "#797966",
          "type": "color"
        },
        "95": {
          "value": "#5b5b4c",
          "type": "color"
        },
        "97": {
          "value": "#47473b",
          "type": "color"
        },
        "05": {
          "value": "#fafaf7",
          "type": "color"
        }
      },
      "sunset": {
        "10": {
          "value": "#fcf6ed",
          "type": "color"
        },
        "20": {
          "value": "#faedd9",
          "type": "color"
        },
        "30": {
          "value": "#f6e0bd",
          "type": "color"
        },
        "40": {
          "value": "#f2d2a0",
          "type": "color"
        },
        "50": {
          "value": "#eec584",
          "type": "color"
        },
        "60": {
          "value": "#d6b177",
          "type": "color"
        },
        "70": {
          "value": "#be9e6a",
          "type": "color"
        },
        "80": {
          "value": "#b39463",
          "type": "color"
        },
        "90": {
          "value": "#8f764f",
          "type": "color"
        },
        "95": {
          "value": "#6b593b",
          "type": "color"
        },
        "97": {
          "value": "#53452e",
          "type": "color"
        },
        "05": {
          "value": "#fdf9f3",
          "type": "color"
        }
      },
      "tan": {
        "10": {
          "value": "#f7f2ec",
          "type": "color"
        },
        "20": {
          "value": "#eee5d9",
          "type": "color"
        },
        "30": {
          "value": "#e1d2bc",
          "type": "color"
        },
        "40": {
          "value": "#d5bea0",
          "type": "color"
        },
        "50": {
          "value": "#c8ab83",
          "type": "color"
        },
        "60": {
          "value": "#b49a76",
          "type": "color"
        },
        "70": {
          "value": "#a08969",
          "type": "color"
        },
        "80": {
          "value": "#968062",
          "type": "color"
        },
        "90": {
          "value": "#78674f",
          "type": "color"
        },
        "95": {
          "value": "#5a4d3b",
          "type": "color"
        },
        "97": {
          "value": "#463c2e",
          "type": "color"
        },
        "05": {
          "value": "#faf7f3",
          "type": "color"
        }
      },
      "battleship": {
        "10": {
          "value": "#eef0ed",
          "type": "color"
        },
        "20": {
          "value": "#dcdfda",
          "type": "color"
        },
        "30": {
          "value": "#c2c8bf",
          "type": "color"
        },
        "40": {
          "value": "#a9b0a3",
          "type": "color"
        },
        "50": {
          "value": "#8f9988",
          "type": "color"
        },
        "60": {
          "value": "#818a7a",
          "type": "color"
        },
        "70": {
          "value": "#727a6d",
          "type": "color"
        },
        "80": {
          "value": "#6b7366",
          "type": "color"
        },
        "90": {
          "value": "#565c52",
          "type": "color"
        },
        "95": {
          "value": "#40453d",
          "type": "color"
        },
        "97": {
          "value": "#323630",
          "type": "color"
        },
        "05": {
          "value": "#f4f5f3",
          "type": "color"
        }
      },
      "cyan": {
        "10": {
          "value": "#e6edee",
          "type": "color"
        },
        "20": {
          "value": "#cad9db",
          "type": "color"
        },
        "30": {
          "value": "#a3bdc1",
          "type": "color"
        },
        "40": {
          "value": "#7ca2a6",
          "type": "color"
        },
        "50": {
          "value": "#55868c",
          "type": "color"
        },
        "60": {
          "value": "#4d797e",
          "type": "color"
        },
        "70": {
          "value": "#446b70",
          "type": "color"
        },
        "80": {
          "value": "#406569",
          "type": "color"
        },
        "90": {
          "value": "#335054",
          "type": "color"
        },
        "95": {
          "value": "#263c3f",
          "type": "color"
        },
        "97": {
          "value": "#1e2f31",
          "type": "color"
        },
        "05": {
          "value": "#eef3f4",
          "type": "color"
        }
      },
      "rose": {
        "10": {
          "value": "#ece8e9",
          "type": "color"
        },
        "20": {
          "value": "#d7cfd2",
          "type": "color"
        },
        "30": {
          "value": "#baabb1",
          "type": "color"
        },
        "40": {
          "value": "#9c878f",
          "type": "color"
        },
        "50": {
          "value": "#7f636e",
          "type": "color"
        },
        "60": {
          "value": "#725963",
          "type": "color"
        },
        "70": {
          "value": "#664f58",
          "type": "color"
        },
        "80": {
          "value": "#5f4a53",
          "type": "color"
        },
        "90": {
          "value": "#4c3b42",
          "type": "color"
        },
        "95": {
          "value": "#392d31",
          "type": "color"
        },
        "97": {
          "value": "#2c2327",
          "type": "color"
        },
        "05": {
          "value": "#f2eff1",
          "type": "color"
        }
      },
      "neutral": {
        "10": {
          "value": "#f5f5f5",
          "type": "color"
        },
        "20": {
          "value": "#f0f0f0",
          "type": "color"
        },
        "30": {
          "value": "#e5e5e5",
          "type": "color"
        },
        "40": {
          "value": "#d9d9d9",
          "type": "color"
        },
        "50": {
          "value": "#bfbfbf",
          "type": "color"
        },
        "60": {
          "value": "#8c8c8c",
          "type": "color"
        },
        "70": {
          "value": "#595959",
          "type": "color"
        },
        "80": {
          "value": "#454545",
          "type": "color"
        },
        "90": {
          "value": "#262626",
          "type": "color"
        },
        "95": {
          "value": "#1f1f1f",
          "type": "color"
        },
        "97": {
          "value": "#141414",
          "type": "color"
        },
        "100": {
          "value": "#000000",
          "type": "color"
        },
        "00": {
          "value": "#ffffff",
          "type": "color"
        },
        "05": {
          "value": "#fcfcfc",
          "type": "color"
        }
      }
    },
    "fontFamilies": {
      "roboto": {
        "value": "Roboto",
        "type": "fontFamilies"
      }
    },
    "lineHeights": {
      "0": {
        "value": "AUTO",
        "type": "lineHeights"
      }
    },
    "fontWeights": {
      "roboto-0": {
        "value": "Light",
        "type": "fontWeights"
      },
      "roboto-1": {
        "value": "Regular",
        "type": "fontWeights"
      },
      "roboto-2": {
        "value": "Condensed Medium",
        "type": "fontWeights"
      },
      "roboto-3": {
        "value": "Medium",
        "type": "fontWeights"
      },
      "roboto-4": {
        "value": "Condensed SemiBold",
        "type": "fontWeights"
      }
    },
    "fontSize": {
      "0": {
        "value": "13",
        "type": "fontSizes"
      },
      "1": {
        "value": "14",
        "type": "fontSizes"
      },
      "2": {
        "value": "16",
        "type": "fontSizes"
      },
      "3": {
        "value": "18",
        "type": "fontSizes"
      },
      "4": {
        "value": "22",
        "type": "fontSizes"
      },
      "5": {
        "value": "28",
        "type": "fontSizes"
      },
      "6": {
        "value": "34",
        "type": "fontSizes"
      }
    },
    "letterSpacing": {
      "0": {
        "value": "0%",
        "type": "letterSpacing"
      }
    },
    "paragraphSpacing": {
      "0": {
        "value": "0",
        "type": "paragraphSpacing"
      }
    },
    "small": {
      "value": {
        "fontFamily": "{fontFamilies.roboto}",
        "fontWeight": "{fontWeights.roboto-0}",
        "lineHeight": "{lineHeights.0}",
        "fontSize": "{fontSize.0}",
        "letterSpacing": "{letterSpacing.0}",
        "paragraphSpacing": "{paragraphSpacing.0}",
        "paragraphIndent": "{paragraphIndent.0}",
        "textCase": "{textCase.none}",
        "textDecoration": "{textDecoration.none}"
      },
      "type": "typography"
    },
    "standard": {
      "value": {
        "fontFamily": "{fontFamilies.roboto}",
        "fontWeight": "{fontWeights.roboto-1}",
        "lineHeight": "{lineHeights.0}",
        "fontSize": "{fontSize.1}",
        "letterSpacing": "{letterSpacing.0}",
        "paragraphSpacing": "{paragraphSpacing.0}",
        "paragraphIndent": "{paragraphIndent.0}",
        "textCase": "{textCase.none}",
        "textDecoration": "{textDecoration.none}"
      },
      "type": "typography"
    },
    "bigger": {
      "value": {
        "fontFamily": "{fontFamilies.roboto}",
        "fontWeight": "{fontWeights.roboto-1}",
        "lineHeight": "{lineHeights.0}",
        "fontSize": "{fontSize.2}",
        "letterSpacing": "{letterSpacing.0}",
        "paragraphSpacing": "{paragraphSpacing.0}",
        "paragraphIndent": "{paragraphIndent.0}",
        "textCase": "{textCase.none}",
        "textDecoration": "{textDecoration.none}"
      },
      "type": "typography"
    },
    "h4": {
      "value": {
        "fontFamily": "{fontFamilies.roboto}",
        "fontWeight": "{fontWeights.roboto-2}",
        "lineHeight": "{lineHeights.0}",
        "fontSize": "{fontSize.3}",
        "letterSpacing": "{letterSpacing.0}",
        "paragraphSpacing": "{paragraphSpacing.0}",
        "paragraphIndent": "{paragraphIndent.0}",
        "textCase": "{textCase.none}",
        "textDecoration": "{textDecoration.none}"
      },
      "type": "typography"
    },
    "h3": {
      "value": {
        "fontFamily": "{fontFamilies.roboto}",
        "fontWeight": "{fontWeights.roboto-3}",
        "lineHeight": "{lineHeights.0}",
        "fontSize": "{fontSize.4}",
        "letterSpacing": "{letterSpacing.0}",
        "paragraphSpacing": "{paragraphSpacing.0}",
        "paragraphIndent": "{paragraphIndent.0}",
        "textCase": "{textCase.none}",
        "textDecoration": "{textDecoration.none}"
      },
      "type": "typography"
    },
    "h2": {
      "value": {
        "fontFamily": "{fontFamilies.roboto}",
        "fontWeight": "{fontWeights.roboto-4}",
        "lineHeight": "{lineHeights.0}",
        "fontSize": "{fontSize.5}",
        "letterSpacing": "{letterSpacing.0}",
        "paragraphSpacing": "{paragraphSpacing.0}",
        "paragraphIndent": "{paragraphIndent.0}",
        "textCase": "{textCase.none}",
        "textDecoration": "{textDecoration.none}"
      },
      "type": "typography"
    },
    "h1": {
      "value": {
        "fontFamily": "{fontFamilies.roboto}",
        "fontWeight": "{fontWeights.roboto-4}",
        "lineHeight": "{lineHeights.0}",
        "fontSize": "{fontSize.6}",
        "letterSpacing": "{letterSpacing.0}",
        "paragraphSpacing": "{paragraphSpacing.0}",
        "paragraphIndent": "{paragraphIndent.0}",
        "textCase": "{textCase.none}",
        "textDecoration": "{textDecoration.none}"
      },
      "type": "typography"
    },
    "textCase": {
      "none": {
        "value": "none",
        "type": "textCase"
      }
    },
    "textDecoration": {
      "none": {
        "value": "none",
        "type": "textDecoration"
      }
    },
    "paragraphIndent": {
      "0": {
        "value": "0px",
        "type": "dimension"
      }
    }
  },
  "$themes": [],
  "$metadata": {
    "tokenSetOrder": [
      "me"
    ]
  }
}